lavender/__init__.py
lavender/__main__.py
lavender/py.typed
lavenderd/__init__.py
llib2to3/Grammar.txt
llib2to3/LICENSE
llib2to3/PatternGrammar.txt
llib2to3/README
llib2to3/__init__.py
llib2to3/pgen2/__init__.py
llib2to3/pgen2/conv.py
llib2to3/pgen2/driver.py
llib2to3/pgen2/grammar.py
llib2to3/pgen2/literals.py
llib2to3/pgen2/parse.py
llib2to3/pgen2/pgen.py
llib2to3/pgen2/token.py
llib2to3/pgen2/tokenize.py
llib2to3/pygram.py
llib2to3/pytree.py
lavender-0.2.1.dist-info/entry_points.txt
lavender-0.2.1.dist-info/LICENSE
lavender-0.2.1.dist-info/WHEEL
lavender-0.2.1.dist-info/METADATA
lavender-0.2.1.dist-info/RECORD
