Metadata-Version: 2.1
Name: lavender
Version: 0.2.1
Summary: The slightly more compromising code formatter.
Home-page: https://github.com/spinda/lavender#readme
License: MIT
Keywords: automation,formatter,black,yapf,autopep8
Author: Michael Smith
Author-email: michael@spinda.net
Requires-Python: >=3.6,<4.0
Classifier: Development Status :: 4 - Beta
Classifier: Environment :: Console
Classifier: Intended Audience :: Developers
Classifier: License :: OSI Approved :: MIT License
Classifier: Operating System :: OS Independent
Classifier: Programming Language :: Python
Classifier: Programming Language :: Python :: 3
Classifier: Programming Language :: Python :: 3 :: Only
Classifier: Programming Language :: Python :: 3.6
Classifier: Programming Language :: Python :: 3.7
Classifier: Programming Language :: Python :: 3.8
Classifier: Programming Language :: Python :: 3.9
Classifier: Topic :: Software Development :: Libraries :: Python Modules
Classifier: Topic :: Software Development :: Quality Assurance
Provides-Extra: d
Requires-Dist: aiohttp (>=3.3.2,<4.0.0); extra == "d"
Requires-Dist: aiohttp_cors (>=0.7.0,<0.8.0); extra == "d"
Requires-Dist: appdirs (>=1.4.0,<2.0.0)
Requires-Dist: click (>=7.1.2,<8.0.0)
Requires-Dist: colorama (>=0.4.3,<0.5.0)
Requires-Dist: dataclasses (>=0.6,<0.9); python_version < "3.7"
Requires-Dist: mypy_extensions (>=0.4.3,<0.5.0)
Requires-Dist: pathspec (>=0.6.0,<0.9)
Requires-Dist: regex (>=2020.1.8)
Requires-Dist: toml (>=0.10.1,<0.11.0)
Requires-Dist: typed-ast (>=1.4.0,<2.0.0)
Requires-Dist: typing_extensions (>=3.7.4,<4.0.0)
Project-URL: Repository, https://github.com/spinda/lavender.git
